emcee_rapper/__init__.py
emcee_rapper/mcmcwrapper.py
emcee_rapper-1.0.0.dist-info/licenses/LICENSE
emcee_rapper-1.0.0.dist-info/METADATA
emcee_rapper-1.0.0.dist-info/WHEEL
emcee_rapper-1.0.0.dist-info/top_level.txt
emcee_rapper-1.0.0.dist-info/RECORD
