Metadata-Version: 2.4
Name: emcee_rapper
Version: 1.0.0
Summary: A wrapper around emcee with plotting tools
Author: Cat, Thomas, Anthony, Andres
Requires-Python: >=3.10
License-File: LICENSE
Requires-Dist: numpy
Requires-Dist: corner
Requires-Dist: matplotlib
Requires-Dist: emcee
Requires-Dist: scipy
Dynamic: author
Dynamic: license-file
Dynamic: requires-dist
Dynamic: requires-python
Dynamic: summary
